CHANGELOG.rst
LICENSE
MANIFEST.in
README.rst
setup.cfg
setup.py
logaugment/__init__.py
logaugment.egg-info/PKG-INFO
logaugment.egg-info/SOURCES.txt
logaugment.egg-info/dependency_links.txt
logaugment.egg-info/top_level.txt